{
 "test": {
           "chat": "Welcome, adventurer! Do you want my help?",
           "answer": [
                     {
                      "chat": "Yes, please",
                      "reply": "great",
                      "action": "shop"
                      },
                      {
                      "chat": "No thanks, just passing by",
                      "reply": "no"
                      }
                      ],
            "great": "That's brilliant!",
            "no": "Your choice."
           }
}